{
    "id": "demon-slayer-mugen-train-la-película",
    "nombre": "Demon Slayer: Mugen Train La Película",
    "poster": "https://cuevana.pro/resize/200/storage/23126/WQ1VklFyD9DKbziNzUzF7AJNl32DOwrXN4fK3bUw.jpg",
    "background": "https://cuevana.pro/resize/1720/storage/23127/VIyitwgYjfvMOmwdl5QcGafzH8mht9fGKHLLjxqp.jpg",
    "año": 2020,
    "descripcion": "Tanjiro y sus compañeros se unen al Pilar de las Llamas Kyojuro Rengoku para investigar una misteriosa serie de desapariciones que han ocurrido dentro del “Tren Infinito”. Poco saben que Enmu, uno de los miembros de las Doce Lunas Demoníacas, también está a bordo y les ha preparado una trampa.",
    "generos": [
        "Accion",
        "Drama",
        "Aventura",
        "Fantasia",
        "Animacion",
        "Anime"
    ],
    "rating": 8,
    "duracion": "1h 57m",
    "tipo": "pelicula",
    "video": "https://akamai.interplanetary.video/?v=aHR0cHM6Ly92aWRoaWRlcGx1cy5jb20vdi80OGh5bWFua2UyNjg="
}